{
    "dimension": 1,
    "variables": [
        "NumJets"
    ],
    "error_type": "absolute",
    "binning": {
        "x": [
            0.0,
            1.0,
            2.0,
            3.0,
            4.0,
            5.0,
            6.0,
            7.0,
            8.0,
            9.0,
            10.0,
            11.0,
            12.0,
            13.0,
            14.0
        ]
    },
    "data": [
        {
            "bin": [
                0.0,
                1.0
            ],
            "value": 1.0,
            "error_low": 0.0,
            "error_high": 0.0
        },
        {
            "bin": [
                1.0,
                2.0
            ],
            "value": 0.9828233163932906,
            "error_low": 0.0,
            "error_high": 0.0
        },
        {
            "bin": [
                2.0,
                3.0
            ],
            "value": 0.9215723575244469,
            "error_low": 0.0,
            "error_high": 0.0
        },
        {
            "bin": [
                3.0,
                4.0
            ],
            "value": 0.8857959448908098,
            "error_low": 0.0,
            "error_high": 0.0
        },
        {
            "bin": [
                4.0,
                5.0
            ],
            "value": 0.8725224788169121,
            "error_low": 0.0,
            "error_high": 0.0
        },
        {
            "bin": [
                5.0,
                6.0
            ],
            "value": 0.865215617647916,
            "error_low": 0.0,
            "error_high": 0.0
        },
        {
            "bin": [
                6.0,
                7.0
            ],
            "value": 0.8518126978990397,
            "error_low": 0.0,
            "error_high": 0.0
        },
        {
            "bin": [
                7.0,
                8.0
            ],
            "value": 0.8225578068106949,
            "error_low": 0.0,
            "error_high": 0.0
        },
        {
            "bin": [
                8.0,
                9.0
            ],
            "value": 0.800957888964249,
            "error_low": 0.0,
            "error_high": 0.0
        },
        {
            "bin": [
                9.0,
                10.0
            ],
            "value": 0.7420964742798933,
            "error_low": 0.0,
            "error_high": 0.0
        },
        {
            "bin": [
                10.0,
                11.0
            ],
            "value": 0.7167456164827721,
            "error_low": 0.0,
            "error_high": 0.0
        },
        {
            "bin": [
                11.0,
                12.0
            ],
            "value": 0.715083735924365,
            "error_low": 0.0,
            "error_high": 0.0
        },
        {
            "bin": [
                12.0,
                13.0
            ],
            "value": 0.6925911437475076,
            "error_low": 0.0,
            "error_high": 0.0
        },
        {
            "bin": [
                13.0,
                14.0
            ],
            "value": 0.7647699155930804,
            "error_low": 0.0,
            "error_high": 0.0
        }
    ]
}