{
    "dimension": 1,
    "variables": [
        "NumJets"
    ],
    "error_type": "absolute",
    "binning": {
        "x": [
            0.0,
            1.0,
            2.0,
            3.0,
            4.0,
            5.0,
            6.0,
            7.0,
            8.0,
            9.0,
            10.0,
            11.0,
            12.0,
            13.0,
            14.0
        ]
    },
    "data": [
        {
            "bin": [
                0.0,
                1.0
            ],
            "value": 1.0,
            "error_low": 0.0,
            "error_high": 0.0
        },
        {
            "bin": [
                1.0,
                2.0
            ],
            "value": 0.9377781993208354,
            "error_low": 0.0,
            "error_high": 0.0
        },
        {
            "bin": [
                2.0,
                3.0
            ],
            "value": 0.8219605644040849,
            "error_low": 0.0,
            "error_high": 0.0
        },
        {
            "bin": [
                3.0,
                4.0
            ],
            "value": 0.8005041473796997,
            "error_low": 0.0,
            "error_high": 0.0
        },
        {
            "bin": [
                4.0,
                5.0
            ],
            "value": 0.7828306601739824,
            "error_low": 0.0,
            "error_high": 0.0
        },
        {
            "bin": [
                5.0,
                6.0
            ],
            "value": 0.7588406544890007,
            "error_low": 0.0,
            "error_high": 0.0
        },
        {
            "bin": [
                6.0,
                7.0
            ],
            "value": 0.7257323789213728,
            "error_low": 0.0,
            "error_high": 0.0
        },
        {
            "bin": [
                7.0,
                8.0
            ],
            "value": 0.6920078724235945,
            "error_low": 0.0,
            "error_high": 0.0
        },
        {
            "bin": [
                8.0,
                9.0
            ],
            "value": 0.6344498737195703,
            "error_low": 0.0,
            "error_high": 0.0
        },
        {
            "bin": [
                9.0,
                10.0
            ],
            "value": 0.5949739635122606,
            "error_low": 0.0,
            "error_high": 0.0
        },
        {
            "bin": [
                10.0,
                11.0
            ],
            "value": 0.563911317002188,
            "error_low": 0.0,
            "error_high": 0.0
        },
        {
            "bin": [
                11.0,
                12.0
            ],
            "value": 0.5159403725363219,
            "error_low": 0.0,
            "error_high": 0.0
        },
        {
            "bin": [
                12.0,
                13.0
            ],
            "value": 0.243277912850653,
            "error_low": 0.0,
            "error_high": 0.0
        },
        {
            "bin": [
                13.0,
                14.0
            ],
            "value": 0.7125631803973366,
            "error_low": 0.0,
            "error_high": 0.0
        }
    ]
}