{
    "dimension": 1,
    "variables": [
        "NumJets"
    ],
    "error_type": "absolute",
    "binning": {
        "x": [
            0.0,
            1.0,
            2.0,
            3.0,
            4.0,
            5.0,
            6.0,
            7.0,
            8.0,
            9.0,
            10.0,
            11.0,
            12.0,
            13.0,
            14.0,
            15.0
        ]
    },
    "data": [
        {
            "bin": [
                0.0,
                1.0
            ],
            "value": 1.0,
            "error_low": 0.0,
            "error_high": 0.0
        },
        {
            "bin": [
                1.0,
                2.0
            ],
            "value": 0.9736693051060373,
            "error_low": 0.0,
            "error_high": 0.0
        },
        {
            "bin": [
                2.0,
                3.0
            ],
            "value": 0.9161057872113811,
            "error_low": 0.0,
            "error_high": 0.0
        },
        {
            "bin": [
                3.0,
                4.0
            ],
            "value": 0.9102161474001643,
            "error_low": 0.0,
            "error_high": 0.0
        },
        {
            "bin": [
                4.0,
                5.0
            ],
            "value": 0.9101630096320672,
            "error_low": 0.0,
            "error_high": 0.0
        },
        {
            "bin": [
                5.0,
                6.0
            ],
            "value": 0.9085841325712207,
            "error_low": 0.0,
            "error_high": 0.0
        },
        {
            "bin": [
                6.0,
                7.0
            ],
            "value": 0.9016678868993533,
            "error_low": 0.0,
            "error_high": 0.0
        },
        {
            "bin": [
                7.0,
                8.0
            ],
            "value": 0.8939309281971812,
            "error_low": 0.0,
            "error_high": 0.0
        },
        {
            "bin": [
                8.0,
                9.0
            ],
            "value": 0.8631476645061242,
            "error_low": 0.0,
            "error_high": 0.0
        },
        {
            "bin": [
                9.0,
                10.0
            ],
            "value": 0.8493423600588179,
            "error_low": 0.0,
            "error_high": 0.0
        },
        {
            "bin": [
                10.0,
                11.0
            ],
            "value": 0.7893897821189935,
            "error_low": 0.0,
            "error_high": 0.0
        },
        {
            "bin": [
                11.0,
                12.0
            ],
            "value": 0.8049683800306348,
            "error_low": 0.0,
            "error_high": 0.0
        },
        {
            "bin": [
                12.0,
                13.0
            ],
            "value": 0.8423035376794346,
            "error_low": 0.0,
            "error_high": 0.0
        },
        {
            "bin": [
                13.0,
                14.0
            ],
            "value": 0.6247220005288554,
            "error_low": 0.0,
            "error_high": 0.0
        },
        {
            "bin": [
                14.0,
                15.0
            ],
            "value": 0.3863224826763449,
            "error_low": 0.0,
            "error_high": 0.0
        }
    ]
}