{
    "dimension": 1,
    "variables": [
        "NumJets"
    ],
    "error_type": "absolute",
    "binning": {
        "x": [
            0.0,
            1.0,
            2.0,
            3.0,
            4.0,
            5.0,
            6.0,
            7.0,
            8.0,
            9.0,
            10.0,
            11.0,
            12.0,
            13.0,
            14.0,
            15.0
        ]
    },
    "data": [
        {
            "bin": [
                0.0,
                1.0
            ],
            "value": 1.0,
            "error_low": 0.0,
            "error_high": 0.0
        },
        {
            "bin": [
                1.0,
                2.0
            ],
            "value": 0.9827699637212252,
            "error_low": 0.0,
            "error_high": 0.0
        },
        {
            "bin": [
                2.0,
                3.0
            ],
            "value": 0.965143222024765,
            "error_low": 0.0,
            "error_high": 0.0
        },
        {
            "bin": [
                3.0,
                4.0
            ],
            "value": 0.9079272826018221,
            "error_low": 0.0,
            "error_high": 0.0
        },
        {
            "bin": [
                4.0,
                5.0
            ],
            "value": 0.8622974963691485,
            "error_low": 0.0,
            "error_high": 0.0
        },
        {
            "bin": [
                5.0,
                6.0
            ],
            "value": 0.8212376187799049,
            "error_low": 0.0,
            "error_high": 0.0
        },
        {
            "bin": [
                6.0,
                7.0
            ],
            "value": 0.7776436333549239,
            "error_low": 0.0,
            "error_high": 0.0
        },
        {
            "bin": [
                7.0,
                8.0
            ],
            "value": 0.7403317708530378,
            "error_low": 0.0,
            "error_high": 0.0
        },
        {
            "bin": [
                8.0,
                9.0
            ],
            "value": 0.7012572184021438,
            "error_low": 0.0,
            "error_high": 0.0
        },
        {
            "bin": [
                9.0,
                10.0
            ],
            "value": 0.6523662399326602,
            "error_low": 0.0,
            "error_high": 0.0
        },
        {
            "bin": [
                10.0,
                11.0
            ],
            "value": 0.5363158946905643,
            "error_low": 0.0,
            "error_high": 0.0
        },
        {
            "bin": [
                11.0,
                12.0
            ],
            "value": 0.46051817155210895,
            "error_low": 0.0,
            "error_high": 0.0
        },
        {
            "bin": [
                12.0,
                13.0
            ],
            "value": 0.589962831386468,
            "error_low": 0.0,
            "error_high": 0.0
        },
        {
            "bin": [
                13.0,
                14.0
            ],
            "value": 0.2587815033010166,
            "error_low": 0.0,
            "error_high": 0.0
        },
        {
            "bin": [
                14.0,
                15.0
            ],
            "value": 0.35187463466616303,
            "error_low": 0.0,
            "error_high": 0.0
        }
    ]
}