{
    "dimension": 1,
    "variables": [
        "NumJets"
    ],
    "error_type": "absolute",
    "binning": {
        "x": [
            0.0,
            1.0,
            2.0,
            3.0,
            4.0,
            5.0,
            6.0,
            7.0,
            8.0,
            9.0,
            10.0,
            11.0,
            12.0,
            13.0,
            14.0
        ]
    },
    "data": [
        {
            "bin": [
                0.0,
                1.0
            ],
            "value": 1.0,
            "error_low": 0.0,
            "error_high": 0.0
        },
        {
            "bin": [
                1.0,
                2.0
            ],
            "value": 0.9733843923804658,
            "error_low": 0.0,
            "error_high": 0.0
        },
        {
            "bin": [
                2.0,
                3.0
            ],
            "value": 0.8351741925223806,
            "error_low": 0.0,
            "error_high": 0.0
        },
        {
            "bin": [
                3.0,
                4.0
            ],
            "value": 0.7980191655930526,
            "error_low": 0.0,
            "error_high": 0.0
        },
        {
            "bin": [
                4.0,
                5.0
            ],
            "value": 0.7475470508505728,
            "error_low": 0.0,
            "error_high": 0.0
        },
        {
            "bin": [
                5.0,
                6.0
            ],
            "value": 0.72965553451004,
            "error_low": 0.0,
            "error_high": 0.0
        },
        {
            "bin": [
                6.0,
                7.0
            ],
            "value": 0.7166380200536177,
            "error_low": 0.0,
            "error_high": 0.0
        },
        {
            "bin": [
                7.0,
                8.0
            ],
            "value": 0.6995126446203644,
            "error_low": 0.0,
            "error_high": 0.0
        },
        {
            "bin": [
                8.0,
                9.0
            ],
            "value": 0.6799963846896574,
            "error_low": 0.0,
            "error_high": 0.0
        },
        {
            "bin": [
                9.0,
                10.0
            ],
            "value": 0.6506245012726919,
            "error_low": 0.0,
            "error_high": 0.0
        },
        {
            "bin": [
                10.0,
                11.0
            ],
            "value": 0.6418832983140452,
            "error_low": 0.0,
            "error_high": 0.0
        },
        {
            "bin": [
                11.0,
                12.0
            ],
            "value": 0.6433437948787958,
            "error_low": 0.0,
            "error_high": 0.0
        },
        {
            "bin": [
                12.0,
                13.0
            ],
            "value": 0.6995590958972824,
            "error_low": 0.0,
            "error_high": 0.0
        },
        {
            "bin": [
                13.0,
                14.0
            ],
            "value": 0.8650936139628649,
            "error_low": 0.0,
            "error_high": 0.0
        }
    ]
}