{
  "dimension": 2,
  "variables": [
    "AbsEta",
    "Pt"
  ],
  "binning": {
    "x": [
      0.0,
      1.2,
      2.4
    ],
    "y": [
      25.0,
      45.0,
      65.0,
      100.0
    ]
  },
  "data": [
    {
      "bin": [
        0.0,
        1.2
      ],
      "values": [
        {
          "bin": [
            25.0,
            45.0
          ],
          "value": 0.6007726759889227,
          "error_low": 0.9833547689506033,
          "error_high": 1.0166452310493967
        },
        {
          "bin": [
            45.0,
            65.0
          ],
          "value": 0.4298781848199545,
          "error_low": 0.9767375960141167,
          "error_high": 1.0232624039858833
        },
        {
          "bin": [
            65.0,
            100.0
          ],
          "value": 0.3826879271070615,
          "error_low": 0.9556725894807916,
          "error_high": 1.0443274105192084
        }
      ]
    },
    {
      "bin": [
        1.2,
        2.4
      ],
      "values": [
        {
          "bin": [
            25.0,
            45.0
          ],
          "value": 0.6441025247486762,
          "error_low": 0.9844745213444056,
          "error_high": 1.0155254786555943
        },
        {
          "bin": [
            45.0,
            65.0
          ],
          "value": 0.4331896551724138,
          "error_low": 0.9769154228855721,
          "error_high": 1.023084577114428
        },
        {
          "bin": [
            65.0,
            100.0
          ],
          "value": 0.38076923076923075,
          "error_low": 0.9416044786524413,
          "error_high": 1.0583955213475587
        }
      ]
    }
  ],
  "error_type": "relative"
}