{
  "dimension": 2,
  "variables": [
    "AbsEta",
    "Pt"
  ],
  "binning": {
    "x": [
      0.0,
      1.479,
      2.5
    ],
    "y": [
      32.0,
      45.0,
      65.0,
      100.0
    ]
  },
  "data": [
    {
      "bin": [
        0.0,
        1.479
      ],
      "values": [
        {
          "bin": [
            32.0,
            45.0
          ],
          "value": 0.5228070175438596,
          "error_low": 0.0,
          "error_high": 0.0
        },
        {
          "bin": [
            45.0,
            65.0
          ],
          "value": 0.5368421052631579,
          "error_low": 0.0,
          "error_high": 0.0
        },
        {
          "bin": [
            65.0,
            100.0
          ],
          "value": 0.5207373271889401,
          "error_low": 0.0,
          "error_high": 0.0
        }
      ]
    },
    {
      "bin": [
        1.479,
        2.5
      ],
      "values": [
        {
          "bin": [
            32.0,
            45.0
          ],
          "value": 0.5319148936170213,
          "error_low": 0.0,
          "error_high": 0.0
        },
        {
          "bin": [
            45.0,
            65.0
          ],
          "value": 0.34523809523809523,
          "error_low": 0.0,
          "error_high": 0.0
        },
        {
          "bin": [
            65.0,
            100.0
          ],
          "value": 0.3258785942492013,
          "error_low": 0.0,
          "error_high": 0.0
        }
      ]
    }
  ],
  "error_type": "relative"
}